Metadata-Version: 2.0
Name: chess-py
Version: 3.3.1
Summary: Python chess client
Home-page: https://github.com/LordDarkula/chess_py
Author: Aubhro Sengupta
Author-email: aubhrosengupta@gmail.com
License: MIT
Platform: MacOS X
Platform: Windows
Platform: Linux
Classifier: Development Status :: 5 - Production/Stable
Classifier: Intended Audience :: Developers
Classifier: License :: OSI Approved :: MIT License
Classifier: Programming Language :: Python :: 3.6
Classifier: Programming Language :: Python :: 2.7
